odoo/addons/account_dashboard_banner_mis_builder/README.rst
odoo/addons/account_dashboard_banner_mis_builder/__init__.py
odoo/addons/account_dashboard_banner_mis_builder/__manifest__.py
odoo/addons/account_dashboard_banner_mis_builder/i18n/account_dashboard_banner_mis_builder.pot
odoo/addons/account_dashboard_banner_mis_builder/i18n/es.po
odoo/addons/account_dashboard_banner_mis_builder/i18n/fr.po
odoo/addons/account_dashboard_banner_mis_builder/i18n/it.po
odoo/addons/account_dashboard_banner_mis_builder/models/__init__.py
odoo/addons/account_dashboard_banner_mis_builder/models/account_dashboard_banner_cell.py
odoo/addons/account_dashboard_banner_mis_builder/readme/CONFIGURE.md
odoo/addons/account_dashboard_banner_mis_builder/readme/CONTRIBUTORS.md
odoo/addons/account_dashboard_banner_mis_builder/readme/DESCRIPTION.md
odoo/addons/account_dashboard_banner_mis_builder/static/description/icon.png
odoo/addons/account_dashboard_banner_mis_builder/static/description/index.html
odoo/addons/account_dashboard_banner_mis_builder/views/account_dashboard_banner_cell.xml
odoo_addon_account_dashboard_banner_mis_builder-18.0.1.0.0.5.dist-info/METADATA
odoo_addon_account_dashboard_banner_mis_builder-18.0.1.0.0.5.dist-info/WHEEL
odoo_addon_account_dashboard_banner_mis_builder-18.0.1.0.0.5.dist-info/top_level.txt
odoo_addon_account_dashboard_banner_mis_builder-18.0.1.0.0.5.dist-info/RECORD
